Metadata-Version: 2.1
Name: python4office
Version: 0.0.1
Summary: python for office
Home-page: http://python4office.cn/upload-pip/
Author: python4office
Author-email: 1957875073@qq.com
License: MIT Licence
Keywords: pip,python4office
Platform: any
